cibopath/__init__.py
cibopath/cli.py
cibopath/github_api.py
cibopath/log.py
cibopath/readme_parser.py
cibopath/scraper.py
cibopath/templates.py
cibopath/user_config.py
cibopath-0.1.0.dist-info/DESCRIPTION.rst
cibopath-0.1.0.dist-info/entry_points.txt
cibopath-0.1.0.dist-info/METADATA
cibopath-0.1.0.dist-info/metadata.json
cibopath-0.1.0.dist-info/RECORD
cibopath-0.1.0.dist-info/top_level.txt
cibopath-0.1.0.dist-info/WHEEL
