Metadata-Version: 2.0
Name: cibopath
Version: 0.1.0
Summary: Search Cookiecutters on GitHub.
Home-page: https://github.com/hackebrot/cibopath
Author: Raphael Pierzina
Author-email: raphael@hackebrot.de
License: BSD
Keywords: cookiecutter,web scraping,asyncio,command-line
Platform: UNKNOWN
Classifier: Development Status :: 3 - Alpha
Classifier: Intended Audience :: Developers
Classifier: License :: OSI Approved :: BSD License
Classifier: Natural Language :: English
Classifier: Operating System :: OS Independent
Classifier: Programming Language :: Python :: 3 :: Only
Classifier: Programming Language :: Python :: 3.5
Classifier: Programming Language :: Python :: Implementation :: CPython
Requires-Dist: click
Requires-Dist: aiohttp
